datasuscommons/__init__.py
datasuscommons/commons.py
datasuscommons/converter.py
datasuscommons/copier.py
datasuscommons/ftpdownload.py
datasuscommons/ftpinfo.py
datasuscommons/ftpinfocollect.py
datasus_commons-0.4.7.dist-info/LICENSE
datasus_commons-0.4.7.dist-info/METADATA
datasus_commons-0.4.7.dist-info/WHEEL
datasus_commons-0.4.7.dist-info/top_level.txt
datasus_commons-0.4.7.dist-info/RECORD
