Metadata-Version: 2.1
Name: datasus-commons
Version: 0.4.7
Summary: Common utilities and functionalities to handle DATASUS ftp repository and files
Home-page: https://github.com/alfonso777/open-datasus-commons
Author: Victoriano Diaz
Author-email: UNKNOWN
License: UNKNOWN
Platform: UNKNOWN
